{"type": "FeatureCollection", "features": [{"geometry": {"type": "Point", "coordinates": [-8.554111, 70.975306]}, "type": "Feature", "properties": {"marker-color": "#4d4", "osmid": "940071", "ssrid": 1211086, "ssrname": "Jan Mayen", "found": true}}, {"geometry": {"type": "Point", "coordinates": [-8.998319, 70.840794]}, "type": "Feature", "properties": {"marker-color": "#4d4", "osmid": "29145189", "ssrid": 1246592, "ssrname": "S\u00f8rkapp", "found": true}}, {"geometry": {"type": "Point", "coordinates": [-7.968514, 71.146867]}, "type": "Feature", "properties": {"marker-color": "#4d4", "osmid": "1056967234", "ssrid": 1246593, "ssrname": "Nordkapp", "found": true}}, {"geometry": {"type": "Point", "coordinates": [-8.169692, 71.085906]}, "type": "Feature", "properties": {"marker-color": "#4d4", "osmid": "1110343685", "ssrid": 1246594, "ssrname": "Beerenberg", "found": true}}]}